slipstream_libcloud_driver-0.1.3-py2.7-nspkg.pth
slipstream/libcloud/__init__.py
slipstream/libcloud/compute_driver.py
slipstream_libcloud_driver-0.1.3.dist-info/DESCRIPTION.rst
slipstream_libcloud_driver-0.1.3.dist-info/METADATA
slipstream_libcloud_driver-0.1.3.dist-info/RECORD
slipstream_libcloud_driver-0.1.3.dist-info/WHEEL
slipstream_libcloud_driver-0.1.3.dist-info/metadata.json
slipstream_libcloud_driver-0.1.3.dist-info/namespace_packages.txt
slipstream_libcloud_driver-0.1.3.dist-info/top_level.txt
