Metadata-Version: 2.0
Name: slipstream-libcloud-driver
Version: 0.1.3
Summary: A libcloud driver for SlipStream.
Home-page: http://sixsq.com/slipstream
Author: SixSq Sarl
Author-email: support@sixsq.com
License: Apache License, Version 2.0
Keywords: slipstream devops libcloud driver
Platform: UNKNOWN
Classifier: Development Status :: 3 - Alpha
Classifier: License :: OSI Approved :: Apache Software License
Classifier: Intended Audience :: Developers
Classifier: Intended Audience :: System Administrators
Classifier: Operating System :: OS Independent
Classifier: Programming Language :: Python
Classifier: Programming Language :: Python :: 2
Classifier: Programming Language :: Python :: 2.6
Classifier: Programming Language :: Python :: 2.7
Classifier: Programming Language :: Python :: 3
Classifier: Programming Language :: Python :: 3.3
Classifier: Programming Language :: Python :: 3.4
Classifier: Topic :: Software Development
Requires-Dist: apache-libcloud (==0.18.0)
Requires-Dist: slipstream-api (>=0.9.1)
